yucca/__init__.py
yucca/paths.py
yucca/_pyinstaller/__init__.py
yucca/_pyinstaller/hook-yucca.py
yucca/documentation/templates/functional_inference.py
yucca/documentation/templates/functional_preprocessing.py
yucca/documentation/templates/functional_training.py
yucca/documentation/templates/template_config.py
yucca/documentation/tests/transforms/viz_torch_transforms.py
yucca/functional/__init__.py
yucca/functional/planning.py
yucca/functional/preprocessing.py
yucca/functional/array_operations/__init__.py
yucca/functional/array_operations/bounding_boxes.py
yucca/functional/array_operations/collate.py
yucca/functional/array_operations/cropping_and_padding.py
yucca/functional/array_operations/filtering.py
yucca/functional/array_operations/matrix_ops.py
yucca/functional/array_operations/normalization.py
yucca/functional/array_operations/transpose.py
yucca/functional/evaluation/__init__.py
yucca/functional/evaluation/confusion_matrix.py
yucca/functional/evaluation/evaluate_folder.py
yucca/functional/evaluation/metrics.py
yucca/functional/evaluation/obj_metrics.py
yucca/functional/evaluation/surface_metrics.py
yucca/functional/evaluation/deepmind_surface_distance/__init__.py
yucca/functional/evaluation/deepmind_surface_distance/lookup_tables.py
yucca/functional/evaluation/deepmind_surface_distance/metrics.py
yucca/functional/testing/__init__.py
yucca/functional/testing/data/__init__.py
yucca/functional/testing/data/array.py
yucca/functional/testing/data/nifti.py
yucca/functional/testing/data/tensor.py
yucca/functional/transforms/__init__.py
yucca/functional/transforms/bias_field.py
yucca/functional/transforms/blur.py
yucca/functional/transforms/croppad.py
yucca/functional/transforms/gamma.py
yucca/functional/transforms/label_transforms.py
yucca/functional/transforms/masking.py
yucca/functional/transforms/motion_ghosting.py
yucca/functional/transforms/noise.py
yucca/functional/transforms/ringing.py
yucca/functional/transforms/sampling.py
yucca-2.3.7.dist-info/licenses/LICENSE
yucca-2.3.7.dist-info/METADATA
yucca-2.3.7.dist-info/WHEEL
yucca-2.3.7.dist-info/entry_points.txt
yucca-2.3.7.dist-info/top_level.txt
yucca-2.3.7.dist-info/RECORD
