Metadata-Version: 2.4
Name: yucca
Version: 2.3.7
Summary: The modern framework for sandbox experimentation and out-of-the box machine learning on medical data.
Author-email: Sebastian Llambias <llambias@live.com>, Asbjørn Munk <9844416+asbjrnmunk@users.noreply.github.com>, Jakob Ambsdorf <20045425+jakobamb@users.noreply.github.com>
Project-URL: Homepage, https://github.com/sllambias/yucca
Project-URL: Bug Tracker, https://github.com/sllambias/yucca/issues
Keywords: deep learning,image segmentation,medical image analysis,medical image segmentation
Classifier: Programming Language :: Python :: 3
Classifier: License :: OSI Approved :: MIT License
Classifier: Operating System :: OS Independent
Requires-Python: >=3.11
License-File: LICENSE
Requires-Dist: batchgenerators>=0.23
Requires-Dist: connected_components_3d>=3.12.4
Requires-Dist: einops>=0.8.0
Requires-Dist: flake8-unused-arguments>=0.0.13
Requires-Dist: fvcore>=0.1.5
Requires-Dist: lightning>=2.2.1
Requires-Dist: matplotlib>=3.8.3
Requires-Dist: monai>=1.3.0
Requires-Dist: nibabel>=5.2.1
Requires-Dist: numpy>=1.26.4
Requires-Dist: pandas>=2.2.1
Requires-Dist: python-dotenv==1.0.0
Requires-Dist: scikit_image>=0.22.0
Requires-Dist: scikit_learn>=1.4.1.post1
Requires-Dist: seaborn>=0.13.2
Requires-Dist: SimpleITK>=2.3.1
Requires-Dist: tqdm>=4.66.2
Requires-Dist: timm>=0.9.8
Requires-Dist: torchmetrics>=1.4.0.post0
Requires-Dist: wandb>=0.16.3
Requires-Dist: weave>=0.39.0
Provides-Extra: test
Requires-Dist: pytest>=7.3; extra == "test"
Requires-Dist: flake8>=6.1.0; extra == "test"
Requires-Dist: black>=23.10.1; extra == "test"
Requires-Dist: mypy>=1.6.0; extra == "test"
Dynamic: license-file
